{
  "type": "stellarium:mnjw4c_type",
  "generator": {
    "type": "minecraft:noise",
    "settings": "stellarium:mnjw4c_noise_gen",
    "biome_source": {
      "type": "minecraft:multi_noise",
      "biomes": [
        {
          "biome": "stellarium:scorched_desert",
          "parameters": {
            "temperature": 0,
            "humidity": -1.0,
            "continentalness": 1.0,
            "erosion": 1.0,
            "weirdness": 0,
            "depth": 0,
            "offset": 0
          }
        },
        {
          "biome": "stellarium:scorched_forest",
          "parameters": {
            "temperature": -1.0,
            "humidity": -0.8,
            "continentalness": 1.0,
            "erosion": 1.6,
            "weirdness": -0.2,
            "depth": 0,
            "offset": 0
          }
        }
      ]
    }
  }
}